README.md
setup.py
reasoningchain/__init__.py
reasoningchain/_run.py
reasoningchain.egg-info/PKG-INFO
reasoningchain.egg-info/SOURCES.txt
reasoningchain.egg-info/dependency_links.txt
reasoningchain.egg-info/entry_points.txt
reasoningchain.egg-info/requires.txt
reasoningchain.egg-info/top_level.txt
reasoningchain/api/__init__.py
reasoningchain/api/baidu.py
reasoningchain/api/closeai.py
reasoningchain/api/google.py
reasoningchain/api/weather.py
reasoningchain/cache/__init__.py
reasoningchain/cache/disk_cache.py
reasoningchain/custom_tools/__init__.py
reasoningchain/custom_tools/base.py
reasoningchain/custom_tools/tools.py
reasoningchain/executor/__init__.py
reasoningchain/executor/sandbox.py
reasoningchain/index/__init__.py
reasoningchain/index/ask.py
reasoningchain/index/doc_index.py
reasoningchain/llms/__init__.py
reasoningchain/llms/dullm.py
reasoningchain/webui/__init__.py
reasoningchain/webui/stui.py
reasoningchain/webui/webui.py