Metadata-Version: 2.1
Name: reasoningchain
Version: 0.0.24
Author: duer
Requires-Python: >=3.8.0
